pyasan/__init__.py
pyasan/apod.py
pyasan/cli.py
pyasan/client.py
pyasan/config.py
pyasan/exceptions.py
pyasan/mars.py
pyasan/mars_models.py
pyasan/models.py
pyasan/techtransfer.py
pyasan/techtransfer_models.py
pyasan-0.4.4.dist-info/licenses/LICENSE
pyasan-0.4.4.dist-info/METADATA
pyasan-0.4.4.dist-info/WHEEL
pyasan-0.4.4.dist-info/entry_points.txt
pyasan-0.4.4.dist-info/top_level.txt
pyasan-0.4.4.dist-info/RECORD
