Metadata-Version: 2.4
Name: pyasan
Version: 0.4.4
Summary: A Python wrapper and CLI for NASA's REST APIs
Author-email: Jeorry Balasabas <jeorry@gmail.com>
License: MIT
Project-URL: Homepage, https://github.com/jeorryb/pyasan
Project-URL: Repository, https://github.com/jeorryb/pyasan
Project-URL: Documentation, https://github.com/jeorryb/pyasan#readme
Project-URL: Bug Tracker, https://github.com/jeorryb/pyasan/issues
Keywords: nasa,api,astronomy,apod,cli
Classifier: Development Status :: 3 - Alpha
Classifier: Intended Audience :: Developers
Classifier: Intended Audience :: Science/Research
Classifier: Programming Language :: Python :: 3
Classifier: Programming Language :: Python :: 3.8
Classifier: Programming Language :: Python :: 3.9
Classifier: Programming Language :: Python :: 3.10
Classifier: Programming Language :: Python :: 3.11
Classifier: Programming Language :: Python :: 3.12
Classifier: Topic :: Scientific/Engineering :: Astronomy
Requires-Python: >=3.8
License-File: LICENSE
Requires-Dist: requests>=2.25.0
Requires-Dist: click>=8.0.0
Requires-Dist: python-dotenv>=0.19.0
Requires-Dist: rich>=12.0.0
Requires-Dist: pydantic>=1.8.0
Provides-Extra: dev
Requires-Dist: pytest>=6.0; extra == "dev"
Requires-Dist: pytest-cov>=2.0; extra == "dev"
Requires-Dist: black>=22.0; extra == "dev"
Requires-Dist: flake8>=4.0; extra == "dev"
Requires-Dist: mypy>=0.900; extra == "dev"
Requires-Dist: types-requests>=2.0; extra == "dev"
Dynamic: license-file
